shazamLyric/__init__.py
shazamLyric-0.0.2.dist-info/LICENSE
shazamLyric-0.0.2.dist-info/METADATA
shazamLyric-0.0.2.dist-info/WHEEL
shazamLyric-0.0.2.dist-info/top_level.txt
shazamLyric-0.0.2.dist-info/RECORD
